srcopsmetrics/__init__.py
srcopsmetrics/bot_knowledge.py
srcopsmetrics/cli.py
srcopsmetrics/enums.py
srcopsmetrics/evaluate_scores.py
srcopsmetrics/exceptions.py
srcopsmetrics/github_handling.py
srcopsmetrics/github_knowledge.py
srcopsmetrics/iterator.py
srcopsmetrics/kebechet_metrics.py
srcopsmetrics/kebechet_sli_slo_metrics.py
srcopsmetrics/metrics.py
srcopsmetrics/processing.py
srcopsmetrics/storage.py
srcopsmetrics/utils.py
srcopsmetrics/entities/__init__.py
srcopsmetrics/entities/code_frequency.py
srcopsmetrics/entities/commit.py
srcopsmetrics/entities/dependency_update.py
srcopsmetrics/entities/fork.py
srcopsmetrics/entities/interface.py
srcopsmetrics/entities/issue.py
srcopsmetrics/entities/issue_event.py
srcopsmetrics/entities/kebechet_update_manager.py
srcopsmetrics/entities/license.py
srcopsmetrics/entities/pull_request.py
srcopsmetrics/entities/pull_request_discussion.py
srcopsmetrics/entities/raw_issue.py
srcopsmetrics/entities/raw_pull_request.py
srcopsmetrics/entities/readme.py
srcopsmetrics/entities/release.py
srcopsmetrics/entities/stargazer.py
srcopsmetrics/entities/template.py
srcopsmetrics/entities/thoth_advise_metrics.py
srcopsmetrics/entities/thoth_metrics.py
srcopsmetrics/entities/thoth_sli_slo.py
srcopsmetrics/entities/thoth_version_manager_metrics.py
srcopsmetrics/entities/traffic_clones.py
srcopsmetrics/entities/traffic_paths.py
srcopsmetrics/entities/traffic_referrers.py
srcopsmetrics/entities/traffic_views.py
srcopsmetrics/entities/tools/__init__.py
srcopsmetrics/entities/tools/knowledge.py
srcopsmetrics/entities/tools/storage.py
srcopsmetrics-2.12.0.dist-info/LICENSE
srcopsmetrics-2.12.0.dist-info/METADATA
srcopsmetrics-2.12.0.dist-info/WHEEL
srcopsmetrics-2.12.0.dist-info/top_level.txt
srcopsmetrics-2.12.0.dist-info/RECORD
