Metadata-Version: 2.1
Name: srcopsmetrics
Version: 2.12.0
Home-page: https://github.com/AICoE/SrcOpsMetrics
Author: Francesco Murdaca, Dominik Tuchyna
Author-email: fmurdaca@redhat.com, xtuchyna@redhat.com
License: GPLv3+
License-File: LICENSE
Requires-Dist: numpy
Requires-Dist: pandas
Requires-Dist: pygithub
Requires-Dist: thoth-storages
Requires-Dist: semver
Requires-Dist: voluptuous
